{
  "engine": "google_sports",
  "params": {
    "kgmid": {
      "required": true,
      "description": "Parameter defines the Google Knowledge Graph ID of the selected entity type. It can be found in Google Search API, Google Sports API, or on Wikidata as \"Freebase ID\".",
      "group": "search_query"
    },
    "gl": {
      "type": "select",
      "options": [
        "af",
        "al",
        "dz",
        "as",
        "ad",
        "ao",
        "ai",
        "aq",
        "ag",
        "ar",
        "am",
        "aw",
        "au",
        "at",
        "az",
        "bs",
        "bh",
        "bd",
        "bb",
        "by",
        "be",
        "bz",
        "bj",
        "bm",
        "bt",
        "bo",
        "ba",
        "bw",
        "bv",
        "br",
        "io",
        "bn",
        "bg",
        "bf",
        "bi",
        "kh",
        "cm",
        "ca",
        "cv",
        "ky",
        "cf",
        "td",
        "cl",
        "cn",
        "cx",
        "cc",
        "co",
        "km",
        "cg",
        "cd",
        "ck",
        "cr",
        "ci",
        "hr",
        "cu",
        "cy",
        "cz",
        "dk",
        "dj",
        "dm",
        "do",
        "ec",
        "eg",
        "sv",
        "gq",
        "er",
        "ee",
        "et",
        "fk",
        "fo",
        "fj",
        "fi",
        "fr",
        "gf",
        "pf",
        "tf",
        "ga",
        "gm",
        "ge",
        "de",
        "gh",
        "gi",
        "gr",
        "gl",
        "gd",
        "gp",
        "gu",
        "gt",
        "gg",
        "gn",
        "gw",
        "gy",
        "ht",
        "hm",
        "va",
        "hn",
        "hk",
        "hu",
        "is",
        "in",
        "id",
        "ir",
        "iq",
        "ie",
        "im",
        "il",
        "it",
        "je",
        "jm",
        "jp",
        "jo",
        "kz",
        "ke",
        "ki",
        "kp",
        "kr",
        "kw",
        "kg",
        "la",
        "lv",
        "lb",
        "ls",
        "lr",
        "ly",
        "li",
        "lt",
        "lu",
        "mo",
        "mk",
        "mg",
        "mw",
        "my",
        "mv",
        "ml",
        "mt",
        "mh",
        "mq",
        "mr",
        "mu",
        "yt",
        "mx",
        "fm",
        "md",
        "mc",
        "mn",
        "me",
        "ms",
        "ma",
        "mz",
        "mm",
        "na",
        "nr",
        "np",
        "nl",
        "an",
        "nc",
        "nz",
        "ni",
        "ne",
        "ng",
        "nu",
        "nf",
        "mp",
        "no",
        "om",
        "pk",
        "pw",
        "ps",
        "pa",
        "pg",
        "py",
        "pe",
        "ph",
        "pn",
        "pl",
        "pt",
        "pr",
        "qa",
        "re",
        "ro",
        "ru",
        "rw",
        "sh",
        "kn",
        "lc",
        "pm",
        "vc",
        "ws",
        "sm",
        "st",
        "sa",
        "sn",
        "rs",
        "sc",
        "sl",
        "sg",
        "sk",
        "si",
        "sb",
        "so",
        "za",
        "gs",
        "es",
        "lk",
        "sd",
        "sr",
        "sj",
        "sz",
        "se",
        "ch",
        "sy",
        "tw",
        "tj",
        "tz",
        "th",
        "tl",
        "tg",
        "tk",
        "to",
        "tt",
        "tn",
        "tr",
        "tm",
        "tc",
        "tv",
        "ug",
        "ua",
        "ae",
        "uk",
        "gb",
        "us",
        "um",
        "uy",
        "uz",
        "vu",
        "ve",
        "vn",
        "vg",
        "vi",
        "wf",
        "eh",
        "ye",
        "zm",
        "zw"
      ],
      "description": "Parameter defines the country to use for the Google search. It's a two-letter country code (e.g., `us` for the United States, `uk` for United Kingdom, or `fr` for France). Head to the Google countries page for a full list of supported Google countries.",
      "group": "localization"
    },
    "hl": {
      "type": "select",
      "options": [
        "af",
        "ak",
        "sq",
        "ws",
        "am",
        "ar",
        "hy",
        "az",
        "eu",
        "be",
        "bem",
        "bn",
        "bh",
        "xx-bork",
        "bs",
        "br",
        "bg",
        "bt",
        "km",
        "ca",
        "chr",
        "ny",
        "zh-cn",
        "zh-tw",
        "co",
        "hr",
        "cs",
        "da",
        "nl",
        "xx-elmer",
        "en",
        "eo",
        "et",
        "ee",
        "fo",
        "tl",
        "fi",
        "fr",
        "fy",
        "gaa",
        "gl",
        "ka",
        "de",
        "el",
        "kl",
        "gn",
        "gu",
        "xx-hacker",
        "ht",
        "ha",
        "haw",
        "iw",
        "he",
        "hi",
        "hu",
        "is",
        "ig",
        "id",
        "ia",
        "ga",
        "it",
        "ja",
        "jw",
        "kn",
        "kk",
        "rw",
        "rn",
        "xx-klingon",
        "kg",
        "ko",
        "kri",
        "ku",
        "ckb",
        "ky",
        "lo",
        "la",
        "lv",
        "ln",
        "lt",
        "loz",
        "lg",
        "ach",
        "mk",
        "mg",
        "ms",
        "ml",
        "mt",
        "mv",
        "mi",
        "mr",
        "mfe",
        "mo",
        "mn",
        "sr-me",
        "my",
        "ne",
        "pcm",
        "nso",
        "no",
        "nn",
        "oc",
        "or",
        "om",
        "ps",
        "fa",
        "xx-pirate",
        "pl",
        "pt",
        "pt-br",
        "pt-pt",
        "pa",
        "qu",
        "ro",
        "rm",
        "nyn",
        "ru",
        "gd",
        "sr",
        "sh",
        "st",
        "tn",
        "crs",
        "sn",
        "sd",
        "si",
        "sk",
        "sl",
        "so",
        "es",
        "es-419",
        "su",
        "sw",
        "sv",
        "tg",
        "ta",
        "tt",
        "te",
        "th",
        "ti",
        "to",
        "lua",
        "tum",
        "tr",
        "tk",
        "tw",
        "ug",
        "uk",
        "ur",
        "uz",
        "vu",
        "vi",
        "cy",
        "wo",
        "xh",
        "yi",
        "yo",
        "zu"
      ],
      "description": "Parameter defines the language to use for the Google search. It's a two-letter language code (e.g., `en` for English, `es` for Spanish, or `fr` for French). Head to the Google languages page for a full list of supported Google languages.",
      "group": "localization"
    },
    "mpd": {
      "description": "Parameter defines the middle time of the league and team games. Games before and after the specified time will be returned. Format (ISO8601 UTC): `YYYY-MM-DDTHH:mm:ssZ` Example: `2026-05-29T12:30:00Z` Parameter cannot be used with moa and mob parameters.",
      "group": "time_period"
    },
    "moa": {
      "description": "Parameter defines the earliest time of the league and team games. Games after the specified time will be returned. Format (ISO8601 UTC): `YYYY-MM-DDTHH:mm:ssZ` Example: `2026-05-29T12:30:00Z` Parameter cannot be used with mpd parameter. Parameter can be used with mob parameter, but should not be later.",
      "group": "time_period"
    },
    "mob": {
      "description": "Parameter defines the latest time of the league and team games. Games before the specified time will be returned. Format (ISO8601 UTC): `YYYY-MM-DDTHH:mm:ssZ` Example: `2026-05-29T12:30:00Z` Parameter cannot be used with mpd parameter. Parameter can be used with moa parameter, but should not be earlier.",
      "group": "time_period"
    },
    "season_kgmid": {
      "description": "Parameter defines the Google Knowledge Graph ID of the specific standings season and should be used alongside the main league or team kgmid. Available seasons can be found in Google Sports API standings results or on Wikidata as \"Freebase ID\". Parameter can be used as a standalone kgmid parameter to fetch tabs other than standings.",
      "group": "advanced_parameters"
    },
    "sp": {
      "type": "select",
      "options": [
        "ft",
        "bs",
        "bb",
        "cr",
        "af",
        "ih",
        "rg"
      ],
      "required": true,
      "description": "Parameter defines the sport of the selected entity type. Options: `ft` - Football `bs` - Basketball `bb` - Baseball `cr` - Cricket `af` - American football `ih` - Ice hockey `rg` - Rugby",
      "group": "advanced_parameters"
    },
    "type": {
      "type": "select",
      "options": [
        "game",
        "league",
        "team"
      ],
      "required": true,
      "description": "Parameter defines the entity type. Options: `game` - Game `league` - League `team` - Team",
      "group": "advanced_parameters"
    },
    "tab": {
      "type": "select",
      "options": [
        "gm",
        "sn",
        "pl",
        "br",
        "st",
        "rn",
        "ov"
      ],
      "description": "Parameter defines the tab on the page of the selected entity type. Options: `gm` - League/Team - Games `sn` - League/Team - Standings `pl` - League/Team - Players `br` - League/Team - Brackets `st` - League - Stats `rn` - League - Rankings `ov` - Game - Overview (American football) Parameter is required for `league` and `team` entity type. Parameter is optional for `game` entity type and should be used only with American football sp value.",
      "group": "advanced_parameters"
    }
  },
  "common_params": {
    "engine": {
      "required": true,
      "description": "Set parameter to `google_sports` to use the Google Sports API engine.",
      "group": "serpapi_parameters"
    },
    "no_cache": {
      "type": "checkbox",
      "description": "Parameter will force SerpApi to fetch the Google Sports results even if a cached version is already present. A cache is served only if the query and all parameters are exactly the same. Cache expires after 1h. Cached searches are free, and are not counted towards your searches per month. It can be set to `false` (default) to allow results from the cache, or `true` to disallow results from the cache. no\\_cache and async parameters should not be used together.",
      "group": "serpapi_parameters"
    },
    "async": {
      "description": "Parameter defines the way you want to submit your search to SerpApi. It can be set to `false` (default) to open an HTTP connection and keep it open until you got your search results, or `true` to just submit your search to SerpApi and retrieve them later. In this case, you'll need to use our Searches Archive API to retrieve your results. async and no\\_cache parameters should not be used together. async should not be used on accounts with Ludicrous Speed enabled.",
      "group": "serpapi_parameters"
    },
    "zero_trace": {
      "description": "Enterprise only. Parameter enables ZeroTrace mode. It can be set to `false` (default) or `true`. Enable this mode to skip storing search parameters, search files, and search metadata on our servers. This may make debugging more difficult.",
      "group": "serpapi_parameters"
    },
    "api_key": {
      "required": true,
      "description": "Parameter defines the SerpApi private key to use.",
      "group": "serpapi_parameters"
    },
    "output": {
      "description": "Parameter defines the final output you want. It can be set to json (default) to get a structured `JSON` of the results, or `html` to get the raw html retrieved.",
      "group": "serpapi_parameters"
    },
    "json_restrictor": {
      "description": "Parameter defines the fields you want to restrict in the outputs for smaller, faster responses. See JSON Restrictor for more details.",
      "group": "serpapi_parameters"
    }
  }
}